fastocrtools/__init__.py
fastocrtools/tools.py
fastocrtools-3.0.2.dist-info/LICENSE.txt
fastocrtools-3.0.2.dist-info/METADATA
fastocrtools-3.0.2.dist-info/WHEEL
fastocrtools-3.0.2.dist-info/top_level.txt
fastocrtools-3.0.2.dist-info/RECORD
