Metadata-Version: 2.1
Name: fastocrtools
Version: 3.0.2
Summary: 利用百度智能云接口完成文字识别操作
Author: SpeakerC
Author-email: 3390988513@qq.com
Classifier: Programming Language :: Python :: 3
Classifier: License :: OSI Approved :: MIT License
Classifier: Operating System :: OS Independent
Requires-Python: >=3.6
License-File: LICENSE.txt
